[
  {
    "title": "Ác độc nữ xứng cùng bạch liên hoa [ xuyên nhanh ]",
    "views": "0.2m",
    "stars": "2.5k",
    "comments": "52",
    "hanViet": "Ác độc nữ phối dữ bạch liên hoa [ khoái xuyên ]",
    "author": "Qua Vân Tê",
    "status": "Hoàn thành",
    "latestChapter": "Phần 226",
    "lastUpdate": "07-08-2020",
    "thanks": "1256 lần",
    "genres": [
      "Nguyên sang",
      "Bách hợp",
      "Cổ đại",
      "Hiện đại",
      "HE",
      "Tình cảm",
      "Mạt thế",
      "Tu chân",
      "Ngọt sủng",
      "Hệ thống",
      "Xuyên nhanh",
      "Chủ công",
      "Hào môn thế gia",
      "Nữ phụ",
      "Vườn trường",
      "Nhẹ nhàng",
      "Kim bài đề cử 🥇"
    ],
    "description": "Tấn Giang VIP2020-02-14 kết thúc\n\nTổng số bình luận: 5413 số lần bị cất chứa cho đến nay: 16844\n\n【 mỗi cái thế giới đều là he】\n\nGiả cao lãnh thật ôn nhu ác độc nữ xứng công x diện mạo chân thực mỹ giả nhu nhược bạch liên hoa chịu\n\nLoan thanh tiêu nhập chức cốt truyện tu chỉnh viện nghiên cứu sau, cái thứ nhất nhiệm vụ liền tao ngộ bình cảnh.\n\nSắm vai ác độc nữ xứng nàng, vốn nên trở thành nam nữ chủ chi gian cảm tình chất xúc tác, kết quả thao tác không lo, bạch liên hoa nữ chủ đối nàng rễ tình đâm sâu……\n\nNh·iếp thật nhi mặt phảng phất non mềm ba tháng đào hoa, e lệ ngượng ngùng dời mắt tình, môi đỏ khẽ mở: Thanh tiêu, ta thích ngươi.\n\nLoan thanh tiêu:…… Ta cũng là!\n\nNhư vậy mỹ nhân, ai bỏ được cự tuyệt?\n\nHệ thống 520: Chờ, từ từ! Đây là tình huống như thế nào?!!\n\n1 vườn trường tiểu tươi mát, ác độc nữ xứng giáo bá x bạch liên hoa hậu giảng đường ( sau khi thành niên mới có thể ở bên nhau, nữ xứng giả giáo bá ) √\n\n520: Ký chủ đại đại ngươi muốn khi dễ nàng, làm nhục nàng, vu hãm nàng, thời khắc mấu chốt nam chủ cứu nàng với nước lửa!\n\nLoan thanh tiêu: Không thành vấn đề.\n\n……\n\n520: Ký chủ đại đại, này phát triển giống như không rất hợp a, vì cái gì nữ chủ sẽ thích một cái khi dễ nàng, làm nhục nàng, vu hãm nàng ác độc nữ xứng???\n\nLoan thanh tiêu rũ mi cười nhạt: Bởi vì nàng có thể nhìn thấu ta tâm.\n\n1 vườn trường tiểu tươi mát, ác độc nữ xứng giáo bá x bạch liên hoa hậu giảng đường √\n\n2 tang thi hoành hành, mạt thế nhà khoa học x hình người mỹ nhân tang thi vương √\n\n3 tu chân thế giới, ác độc sư tôn x bị sư tôn nuôi lớn mỹ nhân lô đỉnh √\n\n4 hào môn công lược, nữ bá tổng x bay lên chi đầu tiểu phượng hoàng √\n\n5 yêu tinh giữa đường, bạch phượng x đào yêu √\n\n6 hút huyết mê tình, nữ học sinh x quỷ hút máu thân vương √\n\n7 Long Ngạo Thiên hậu cung, vị hôn thê x tiểu thanh mai √\n\n8 ta có sáu cái tình địch √\n\n9 ngụy trang bạch nguyệt quang, ngụy trang giả x bạch nguyệt quang √\n\nend nguyên thế giới, nghèo x chán đời √\n\n……\n\nĐọc phải biết\n\n1 hai người chỉ có lẫn nhau.\n\n2 tên bên ngoài đều bất biến, loan thanh tiêu có ký ức.\n\n3 thật cường x giả nhược, hai người đều rất lợi hại.\n\nTag: Yêu sâu sắcNữ xứngNgọt vănMau xuyên\n\nTừ khóa tìm kiếm: Vai chính: Loan thanh tiêu, Nh·iếp thật nhi ┃ vai phụ: Kết thúc văn 《 pháo hôi cùng bạch nguyệt quang ［ mau xuyên gl］》, tiếp đương văn 《 chim hoàng yến cùng tiểu pháo hôi ［ mau xuyên ］》 ┃ cái khác:\n\nMột câu tóm tắt: Ác độc nữ xứng c·ướp đi nữ chủ",
    "chapters": [
      {
        "title": "Phần 1",
        "link": "/truyen/ac-doc-nu-xung-cung-bach-lien-hoa-xuyen-/phan-1-XnWvrsQsRA1Mclen"
      },
      {
        "title": "Phần 2",
        "link": "/truyen/ac-doc-nu-xung-cung-bach-lien-hoa-xuyen-/phan-2-XnWvrsQsRA1Mcleo"
      },
      {
        "title": "Phần 3",
        "link": "/truyen/ac-doc-nu-xung-cung-bach-lien-hoa-xuyen-/phan-3-XnWvrsQsRA1Mclep"
      },
      {
        "title": "Phần 4",
        "link": "/truyen/ac-doc-nu-xung-cung-bach-lien-hoa-xuyen-/phan-4-XnWvrsQsRA1Mcleq"
      },
      {
        "title": "Phần 5",
        "link": "/truyen/ac-doc-nu-xung-cung-bach-lien-hoa-xuyen-/phan-5-XnWvrsQsRA1Mcler"
      },
      {
        "title": "Phần 6",
        "link": "/truyen/ac-doc-nu-xung-cung-bach-lien-hoa-xuyen-/phan-6-XnWvrsQsRA1Mcles"
      },
      {
        "title": "Phần 7",
        "link": "/truyen/ac-doc-nu-xung-cung-bach-lien-hoa-xuyen-/phan-7-XnWvrsQsRA1Mclet"
      },
      {
        "title": "Phần 8",
        "link": "/truyen/ac-doc-nu-xung-cung-bach-lien-hoa-xuyen-/phan-8-XnWvrsQsRA1Mcleu"
      },
      {
        "title": "Phần 9",
        "link": "/truyen/ac-doc-nu-xung-cung-bach-lien-hoa-xuyen-/phan-9-XnWvrsQsRA1Mclev"
      },
      {
        "title": "Phần 10",
        "link": "/truyen/ac-doc-nu-xung-cung-bach-lien-hoa-xuyen-/phan-10-XnWvrsQsRA1Mclew"
      },
      {
        "title": "Phần 11",
        "link": "/truyen/ac-doc-nu-xung-cung-bach-lien-hoa-xuyen-/phan-11-XnWvrsQsRA1Mclex"
      },
      {
        "title": "Phần 12",
        "link": "/truyen/ac-doc-nu-xung-cung-bach-lien-hoa-xuyen-/phan-12-XnWvrsQsRA1Mcley"
      },
      {
        "title": "Phần 13",
        "link": "/truyen/ac-doc-nu-xung-cung-bach-lien-hoa-xuyen-/phan-13-XnWvrsQsRA1Mclez"
      },
      {
        "title": "Phần 14",
        "link": "/truyen/ac-doc-nu-xung-cung-bach-lien-hoa-xuyen-/phan-14-XnWvrsQsRA1Mcle0"
      },
      {
        "title": "Phần 15",
        "link": "/truyen/ac-doc-nu-xung-cung-bach-lien-hoa-xuyen-/phan-15-XnWvrsQsRA1Mcle1"
      },
      {
        "title": "Phần 16",
        "link": "/truyen/ac-doc-nu-xung-cung-bach-lien-hoa-xuyen-/phan-16-XnWvrsQsRA1Mcle2"
      },
      {
        "title": "Phần 17",
        "link": "/truyen/ac-doc-nu-xung-cung-bach-lien-hoa-xuyen-/phan-17-XnWvrsQsRA1Mcle3"
      },
      {
        "title": "Phần 18",
        "link": "/truyen/ac-doc-nu-xung-cung-bach-lien-hoa-xuyen-/phan-18-XnWvrsQsRA1Mcle4"
      },
      {
        "title": "Phần 19",
        "link": "/truyen/ac-doc-nu-xung-cung-bach-lien-hoa-xuyen-/phan-19-XnWvrsQsRA1Mcle5"
      },
      {
        "title": "Phần 20",
        "link": "/truyen/ac-doc-nu-xung-cung-bach-lien-hoa-xuyen-/phan-20-XnWvrsQsRA1Mcle6"
      },
      {
        "title": "Phần 21",
        "link": "/truyen/ac-doc-nu-xung-cung-bach-lien-hoa-xuyen-/phan-21-XnWvrsQsRA1Mcle7"
      },
      {
        "title": "Phần 22",
        "link": "/truyen/ac-doc-nu-xung-cung-bach-lien-hoa-xuyen-/phan-22-XnWvrsQsRA1Mcle8"
      },
      {
        "title": "Phần 23",
        "link": "/truyen/ac-doc-nu-xung-cung-bach-lien-hoa-xuyen-/phan-23-XnWvrsQsRA1Mcle9"
      },
      {
        "title": "Phần 24",
        "link": "/truyen/ac-doc-nu-xung-cung-bach-lien-hoa-xuyen-/phan-24-XnWvrsQsRA1Mcle%7E"
      },
      {
        "title": "Phần 25",
        "link": "/truyen/ac-doc-nu-xung-cung-bach-lien-hoa-xuyen-/phan-25-XnWvrsQsRA1Mcle_"
      },
      {
        "title": "Phần 26",
        "link": "/truyen/ac-doc-nu-xung-cung-bach-lien-hoa-xuyen-/phan-26-XnWvrsQsRA1MclfA"
      },
      {
        "title": "Phần 27",
        "link": "/truyen/ac-doc-nu-xung-cung-bach-lien-hoa-xuyen-/phan-27-XnWvrsQsRA1MclfB"
      },
      {
        "title": "Phần 28",
        "link": "/truyen/ac-doc-nu-xung-cung-bach-lien-hoa-xuyen-/phan-28-XnWvrsQsRA1MclfC"
      },
      {
        "title": "Phần 29",
        "link": "/truyen/ac-doc-nu-xung-cung-bach-lien-hoa-xuyen-/phan-29-XnWvrsQsRA1MclfD"
      },
      {
        "title": "Phần 30",
        "link": "/truyen/ac-doc-nu-xung-cung-bach-lien-hoa-xuyen-/phan-30-XnWvrsQsRA1MclfE"
      },
      {
        "title": "Phần 31",
        "link": "/truyen/ac-doc-nu-xung-cung-bach-lien-hoa-xuyen-/phan-31-XnWvrsQsRA1MclfF"
      },
      {
        "title": "Phần 32",
        "link": "/truyen/ac-doc-nu-xung-cung-bach-lien-hoa-xuyen-/phan-32-XnWvrsQsRA1MclfG"
      },
      {
        "title": "Phần 33",
        "link": "/truyen/ac-doc-nu-xung-cung-bach-lien-hoa-xuyen-/phan-33-XnWvrsQsRA1MclfH"
      },
      {
        "title": "Phần 34",
        "link": "/truyen/ac-doc-nu-xung-cung-bach-lien-hoa-xuyen-/phan-34-XnWvrsQsRA1MclfI"
      },
      {
        "title": "Phần 35",
        "link": "/truyen/ac-doc-nu-xung-cung-bach-lien-hoa-xuyen-/phan-35-XnWvrsQsRA1MclfJ"
      },
      {
        "title": "Phần 36",
        "link": "/truyen/ac-doc-nu-xung-cung-bach-lien-hoa-xuyen-/phan-36-XnWvrsQsRA1MclfK"
      },
      {
        "title": "Phần 37",
        "link": "/truyen/ac-doc-nu-xung-cung-bach-lien-hoa-xuyen-/phan-37-XnWvrsQsRA1MclfL"
      },
      {
        "title": "Phần 38",
        "link": "/truyen/ac-doc-nu-xung-cung-bach-lien-hoa-xuyen-/phan-38-XnWvrsQsRA1MclfM"
      },
      {
        "title": "Phần 39",
        "link": "/truyen/ac-doc-nu-xung-cung-bach-lien-hoa-xuyen-/phan-39-XnWvrsQsRA1MclfN"
      },
      {
        "title": "Phần 40",
        "link": "/truyen/ac-doc-nu-xung-cung-bach-lien-hoa-xuyen-/phan-40-XnWvrsQsRA1MclfO"
      },
      {
        "title": "Phần 41",
        "link": "/truyen/ac-doc-nu-xung-cung-bach-lien-hoa-xuyen-/phan-41-XnWvrsQsRA1MclfP"
      },
      {
        "title": "Phần 42",
        "link": "/truyen/ac-doc-nu-xung-cung-bach-lien-hoa-xuyen-/phan-42-XnWvrsQsRA1MclfQ"
      },
      {
        "title": "Phần 43",
        "link": "/truyen/ac-doc-nu-xung-cung-bach-lien-hoa-xuyen-/phan-43-XnWvrsQsRA1MclfR"
      },
      {
        "title": "Phần 44",
        "link": "/truyen/ac-doc-nu-xung-cung-bach-lien-hoa-xuyen-/phan-44-XnWvrsQsRA1MclfS"
      },
      {
        "title": "Phần 45",
        "link": "/truyen/ac-doc-nu-xung-cung-bach-lien-hoa-xuyen-/phan-45-XnWvrsQsRA1MclfT"
      },
      {
        "title": "Phần 46",
        "link": "/truyen/ac-doc-nu-xung-cung-bach-lien-hoa-xuyen-/phan-46-XnWvrsQsRA1MclfU"
      },
      {
        "title": "Phần 47",
        "link": "/truyen/ac-doc-nu-xung-cung-bach-lien-hoa-xuyen-/phan-47-XnWvrsQsRA1MclfV"
      },
      {
        "title": "Phần 48",
        "link": "/truyen/ac-doc-nu-xung-cung-bach-lien-hoa-xuyen-/phan-48-XnWvrsQsRA1MclfW"
      },
      {
        "title": "Phần 49",
        "link": "/truyen/ac-doc-nu-xung-cung-bach-lien-hoa-xuyen-/phan-49-XnWvrsQsRA1MclfX"
      },
      {
        "title": "Phần 50",
        "link": "/truyen/ac-doc-nu-xung-cung-bach-lien-hoa-xuyen-/phan-50-XnWvrsQsRA1MclfY"
      },
      {
        "title": "Phần 51",
        "link": "/truyen/ac-doc-nu-xung-cung-bach-lien-hoa-xuyen-/phan-51-XnWvrsQsRA1MclfZ"
      },
      {
        "title": "Phần 52",
        "link": "/truyen/ac-doc-nu-xung-cung-bach-lien-hoa-xuyen-/phan-52-XnWvrsQsRA1Mclfa"
      },
      {
        "title": "Phần 53",
        "link": "/truyen/ac-doc-nu-xung-cung-bach-lien-hoa-xuyen-/phan-53-XnWvrsQsRA1Mclfb"
      },
      {
        "title": "Phần 54",
        "link": "/truyen/ac-doc-nu-xung-cung-bach-lien-hoa-xuyen-/phan-54-XnWvrsQsRA1Mclfc"
      },
      {
        "title": "Phần 55",
        "link": "/truyen/ac-doc-nu-xung-cung-bach-lien-hoa-xuyen-/phan-55-XnWvrsQsRA1Mclfd"
      },
      {
        "title": "Phần 56",
        "link": "/truyen/ac-doc-nu-xung-cung-bach-lien-hoa-xuyen-/phan-56-XnWvrsQsRA1Mclfe"
      },
      {
        "title": "Phần 57",
        "link": "/truyen/ac-doc-nu-xung-cung-bach-lien-hoa-xuyen-/phan-57-XnWvrsQsRA1Mclff"
      },
      {
        "title": "Phần 58",
        "link": "/truyen/ac-doc-nu-xung-cung-bach-lien-hoa-xuyen-/phan-58-XnWvrsQsRA1Mclfg"
      },
      {
        "title": "Phần 59",
        "link": "/truyen/ac-doc-nu-xung-cung-bach-lien-hoa-xuyen-/phan-59-XnWvrsQsRA1Mclfh"
      },
      {
        "title": "Phần 60",
        "link": "/truyen/ac-doc-nu-xung-cung-bach-lien-hoa-xuyen-/phan-60-XnWvrsQsRA1Mclfi"
      },
      {
        "title": "Phần 61",
        "link": "/truyen/ac-doc-nu-xung-cung-bach-lien-hoa-xuyen-/phan-61-XnWvrsQsRA1Mclfj"
      },
      {
        "title": "Phần 62",
        "link": "/truyen/ac-doc-nu-xung-cung-bach-lien-hoa-xuyen-/phan-62-XnWvrsQsRA1Mclfk"
      },
      {
        "title": "Phần 63",
        "link": "/truyen/ac-doc-nu-xung-cung-bach-lien-hoa-xuyen-/phan-63-XnWvrsQsRA1Mclfl"
      },
      {
        "title": "Phần 64",
        "link": "/truyen/ac-doc-nu-xung-cung-bach-lien-hoa-xuyen-/phan-64-XnWvrsQsRA1Mclfm"
      },
      {
        "title": "Phần 65",
        "link": "/truyen/ac-doc-nu-xung-cung-bach-lien-hoa-xuyen-/phan-65-XnWvrsQsRA1Mclfn"
      },
      {
        "title": "Phần 66",
        "link": "/truyen/ac-doc-nu-xung-cung-bach-lien-hoa-xuyen-/phan-66-XnWvrsQsRA1Mclfo"
      },
      {
        "title": "Phần 67",
        "link": "/truyen/ac-doc-nu-xung-cung-bach-lien-hoa-xuyen-/phan-67-XnWvrsQsRA1Mclfp"
      },
      {
        "title": "Phần 68",
        "link": "/truyen/ac-doc-nu-xung-cung-bach-lien-hoa-xuyen-/phan-68-XnWvrsQsRA1Mclfq"
      },
      {
        "title": "Phần 69",
        "link": "/truyen/ac-doc-nu-xung-cung-bach-lien-hoa-xuyen-/phan-69-XnWvrsQsRA1Mclfr"
      },
      {
        "title": "Phần 70",
        "link": "/truyen/ac-doc-nu-xung-cung-bach-lien-hoa-xuyen-/phan-70-XnWvrsQsRA1Mclfs"
      },
      {
        "title": "Phần 71",
        "link": "/truyen/ac-doc-nu-xung-cung-bach-lien-hoa-xuyen-/phan-71-XnWvrsQsRA1Mclft"
      },
      {
        "title": "Phần 72",
        "link": "/truyen/ac-doc-nu-xung-cung-bach-lien-hoa-xuyen-/phan-72-XnWvrsQsRA1Mclfu"
      },
      {
        "title": "Phần 73",
        "link": "/truyen/ac-doc-nu-xung-cung-bach-lien-hoa-xuyen-/phan-73-XnWvrsQsRA1Mclfv"
      },
      {
        "title": "Phần 74",
        "link": "/truyen/ac-doc-nu-xung-cung-bach-lien-hoa-xuyen-/phan-74-XnWvrsQsRA1Mclfw"
      },
      {
        "title": "Phần 75",
        "link": "/truyen/ac-doc-nu-xung-cung-bach-lien-hoa-xuyen-/phan-75-XnWvrsQsRA1Mclfx"
      },
      {
        "title": "Phần 76",
        "link": "/truyen/ac-doc-nu-xung-cung-bach-lien-hoa-xuyen-/phan-76-XnWvrsQsRA1Mclfy"
      },
      {
        "title": "Phần 77",
        "link": "/truyen/ac-doc-nu-xung-cung-bach-lien-hoa-xuyen-/phan-77-XnWvrsQsRA1Mclfz"
      },
      {
        "title": "Phần 78",
        "link": "/truyen/ac-doc-nu-xung-cung-bach-lien-hoa-xuyen-/phan-78-XnWvrsQsRA1Mclf0"
      },
      {
        "title": "Phần 79",
        "link": "/truyen/ac-doc-nu-xung-cung-bach-lien-hoa-xuyen-/phan-79-XnWvrsQsRA1Mclf1"
      },
      {
        "title": "Phần 80",
        "link": "/truyen/ac-doc-nu-xung-cung-bach-lien-hoa-xuyen-/phan-80-XnWvrsQsRA1Mclf2"
      },
      {
        "title": "Phần 81",
        "link": "/truyen/ac-doc-nu-xung-cung-bach-lien-hoa-xuyen-/phan-81-XnWvrsQsRA1Mclf3"
      },
      {
        "title": "Phần 82",
        "link": "/truyen/ac-doc-nu-xung-cung-bach-lien-hoa-xuyen-/phan-82-XnWvrsQsRA1Mclf4"
      },
      {
        "title": "Phần 83",
        "link": "/truyen/ac-doc-nu-xung-cung-bach-lien-hoa-xuyen-/phan-83-XnWvrsQsRA1Mclf5"
      },
      {
        "title": "Phần 84",
        "link": "/truyen/ac-doc-nu-xung-cung-bach-lien-hoa-xuyen-/phan-84-XnWvrsQsRA1Mclf6"
      },
      {
        "title": "Phần 85",
        "link": "/truyen/ac-doc-nu-xung-cung-bach-lien-hoa-xuyen-/phan-85-XnWvrsQsRA1Mclf7"
      },
      {
        "title": "Phần 86",
        "link": "/truyen/ac-doc-nu-xung-cung-bach-lien-hoa-xuyen-/phan-86-XnWvrsQsRA1Mclf8"
      },
      {
        "title": "Phần 87",
        "link": "/truyen/ac-doc-nu-xung-cung-bach-lien-hoa-xuyen-/phan-87-XnWvrsQsRA1Mclf9"
      },
      {
        "title": "Phần 88",
        "link": "/truyen/ac-doc-nu-xung-cung-bach-lien-hoa-xuyen-/phan-88-XnWvrsQsRA1Mclf%7E"
      },
      {
        "title": "Phần 89",
        "link": "/truyen/ac-doc-nu-xung-cung-bach-lien-hoa-xuyen-/phan-89-XnWvrsQsRA1Mclf_"
      },
      {
        "title": "Phần 90",
        "link": "/truyen/ac-doc-nu-xung-cung-bach-lien-hoa-xuyen-/phan-90-XnWvrsQsRA1MclgA"
      },
      {
        "title": "Phần 91",
        "link": "/truyen/ac-doc-nu-xung-cung-bach-lien-hoa-xuyen-/phan-91-XnWvrsQsRA1MclgB"
      },
      {
        "title": "Phần 92",
        "link": "/truyen/ac-doc-nu-xung-cung-bach-lien-hoa-xuyen-/phan-92-XnWvrsQsRA1MclgC"
      },
      {
        "title": "Phần 93",
        "link": "/truyen/ac-doc-nu-xung-cung-bach-lien-hoa-xuyen-/phan-93-XnWvrsQsRA1MclgD"
      },
      {
        "title": "Phần 94",
        "link": "/truyen/ac-doc-nu-xung-cung-bach-lien-hoa-xuyen-/phan-94-XnWvrsQsRA1MclgE"
      },
      {
        "title": "Phần 95",
        "link": "/truyen/ac-doc-nu-xung-cung-bach-lien-hoa-xuyen-/phan-95-XnWvrsQsRA1MclgF"
      },
      {
        "title": "Phần 96",
        "link": "/truyen/ac-doc-nu-xung-cung-bach-lien-hoa-xuyen-/phan-96-XnWvrsQsRA1MclgG"
      },
      {
        "title": "Phần 97",
        "link": "/truyen/ac-doc-nu-xung-cung-bach-lien-hoa-xuyen-/phan-97-XnWvrsQsRA1MclgH"
      },
      {
        "title": "Phần 98",
        "link": "/truyen/ac-doc-nu-xung-cung-bach-lien-hoa-xuyen-/phan-98-XnWvrsQsRA1MclgI"
      },
      {
        "title": "Phần 99",
        "link": "/truyen/ac-doc-nu-xung-cung-bach-lien-hoa-xuyen-/phan-99-XnWvrsQsRA1MclgJ"
      },
      {
        "title": "Phần 100",
        "link": "/truyen/ac-doc-nu-xung-cung-bach-lien-hoa-xuyen-/phan-100-XnWvrsQsRA1MclgK"
      },
      {
        "title": "Phần 101",
        "link": "/truyen/ac-doc-nu-xung-cung-bach-lien-hoa-xuyen-/phan-101-XnWvrsQsRA1MclgL"
      },
      {
        "title": "Phần 102",
        "link": "/truyen/ac-doc-nu-xung-cung-bach-lien-hoa-xuyen-/phan-102-XnWvrsQsRA1MclgM"
      },
      {
        "title": "Phần 103",
        "link": "/truyen/ac-doc-nu-xung-cung-bach-lien-hoa-xuyen-/phan-103-XnWvrsQsRA1MclgN"
      },
      {
        "title": "Phần 104",
        "link": "/truyen/ac-doc-nu-xung-cung-bach-lien-hoa-xuyen-/phan-104-XnWvrsQsRA1MclgO"
      },
      {
        "title": "Phần 105",
        "link": "/truyen/ac-doc-nu-xung-cung-bach-lien-hoa-xuyen-/phan-105-XnWvrsQsRA1MclgP"
      },
      {
        "title": "Phần 106",
        "link": "/truyen/ac-doc-nu-xung-cung-bach-lien-hoa-xuyen-/phan-106-XnWvrsQsRA1MclgQ"
      },
      {
        "title": "Phần 107",
        "link": "/truyen/ac-doc-nu-xung-cung-bach-lien-hoa-xuyen-/phan-107-XnWvrsQsRA1MclgR"
      },
      {
        "title": "Phần 108",
        "link": "/truyen/ac-doc-nu-xung-cung-bach-lien-hoa-xuyen-/phan-108-XnWvrsQsRA1MclgS"
      },
      {
        "title": "Phần 109",
        "link": "/truyen/ac-doc-nu-xung-cung-bach-lien-hoa-xuyen-/phan-109-XnWvrsQsRA1MclgT"
      },
      {
        "title": "Phần 110",
        "link": "/truyen/ac-doc-nu-xung-cung-bach-lien-hoa-xuyen-/phan-110-XnWvrsQsRA1MclgU"
      },
      {
        "title": "Phần 111",
        "link": "/truyen/ac-doc-nu-xung-cung-bach-lien-hoa-xuyen-/phan-111-XnWvrsQsRA1MclgV"
      },
      {
        "title": "Phần 112",
        "link": "/truyen/ac-doc-nu-xung-cung-bach-lien-hoa-xuyen-/phan-112-XnWvrsQsRA1MclgW"
      },
      {
        "title": "Phần 113",
        "link": "/truyen/ac-doc-nu-xung-cung-bach-lien-hoa-xuyen-/phan-113-XnWvrsQsRA1MclgX"
      },
      {
        "title": "Phần 114",
        "link": "/truyen/ac-doc-nu-xung-cung-bach-lien-hoa-xuyen-/phan-114-XnWvrsQsRA1MclgY"
      },
      {
        "title": "Phần 115",
        "link": "/truyen/ac-doc-nu-xung-cung-bach-lien-hoa-xuyen-/phan-115-XnWvrsQsRA1MclgZ"
      },
      {
        "title": "Phần 116",
        "link": "/truyen/ac-doc-nu-xung-cung-bach-lien-hoa-xuyen-/phan-116-XnWvrsQsRA1Mclga"
      },
      {
        "title": "Phần 117",
        "link": "/truyen/ac-doc-nu-xung-cung-bach-lien-hoa-xuyen-/phan-117-XnWvrsQsRA1Mclgb"
      },
      {
        "title": "Phần 118",
        "link": "/truyen/ac-doc-nu-xung-cung-bach-lien-hoa-xuyen-/phan-118-XnWvrsQsRA1Mclgc"
      },
      {
        "title": "Phần 119",
        "link": "/truyen/ac-doc-nu-xung-cung-bach-lien-hoa-xuyen-/phan-119-XnWvrsQsRA1Mclgd"
      },
      {
        "title": "Phần 120",
        "link": "/truyen/ac-doc-nu-xung-cung-bach-lien-hoa-xuyen-/phan-120-XnWvrsQsRA1Mclge"
      },
      {
        "title": "Phần 121",
        "link": "/truyen/ac-doc-nu-xung-cung-bach-lien-hoa-xuyen-/phan-121-XnWvrsQsRA1Mclgf"
      },
      {
        "title": "Phần 122",
        "link": "/truyen/ac-doc-nu-xung-cung-bach-lien-hoa-xuyen-/phan-122-XnWvrsQsRA1Mclgg"
      },
      {
        "title": "Phần 123",
        "link": "/truyen/ac-doc-nu-xung-cung-bach-lien-hoa-xuyen-/phan-123-XnWvrsQsRA1Mclgh"
      },
      {
        "title": "Phần 124",
        "link": "/truyen/ac-doc-nu-xung-cung-bach-lien-hoa-xuyen-/phan-124-XnWvrsQsRA1Mclgi"
      },
      {
        "title": "Phần 125",
        "link": "/truyen/ac-doc-nu-xung-cung-bach-lien-hoa-xuyen-/phan-125-XnWvrsQsRA1Mclgj"
      },
      {
        "title": "Phần 126",
        "link": "/truyen/ac-doc-nu-xung-cung-bach-lien-hoa-xuyen-/phan-126-XnWvrsQsRA1Mclgk"
      },
      {
        "title": "Phần 127",
        "link": "/truyen/ac-doc-nu-xung-cung-bach-lien-hoa-xuyen-/phan-127-XnWvrsQsRA1Mclgl"
      },
      {
        "title": "Phần 128",
        "link": "/truyen/ac-doc-nu-xung-cung-bach-lien-hoa-xuyen-/phan-128-XnWvrsQsRA1Mclgm"
      },
      {
        "title": "Phần 129",
        "link": "/truyen/ac-doc-nu-xung-cung-bach-lien-hoa-xuyen-/phan-129-XnWvrsQsRA1Mclgn"
      },
      {
        "title": "Phần 130",
        "link": "/truyen/ac-doc-nu-xung-cung-bach-lien-hoa-xuyen-/phan-130-XnWvrsQsRA1Mclgo"
      },
      {
        "title": "Phần 131",
        "link": "/truyen/ac-doc-nu-xung-cung-bach-lien-hoa-xuyen-/phan-131-XnWvrsQsRA1Mclgp"
      },
      {
        "title": "Phần 132",
        "link": "/truyen/ac-doc-nu-xung-cung-bach-lien-hoa-xuyen-/phan-132-XnWvrsQsRA1Mclgq"
      },
      {
        "title": "Phần 133",
        "link": "/truyen/ac-doc-nu-xung-cung-bach-lien-hoa-xuyen-/phan-133-XnWvrsQsRA1Mclgr"
      },
      {
        "title": "Phần 134",
        "link": "/truyen/ac-doc-nu-xung-cung-bach-lien-hoa-xuyen-/phan-134-XnWvrsQsRA1Mclgs"
      },
      {
        "title": "Phần 135",
        "link": "/truyen/ac-doc-nu-xung-cung-bach-lien-hoa-xuyen-/phan-135-XnWvrsQsRA1Mclgt"
      },
      {
        "title": "Phần 136",
        "link": "/truyen/ac-doc-nu-xung-cung-bach-lien-hoa-xuyen-/phan-136-XnWvrsQsRA1Mclgu"
      },
      {
        "title": "Phần 137",
        "link": "/truyen/ac-doc-nu-xung-cung-bach-lien-hoa-xuyen-/phan-137-XnWvrsQsRA1Mclgv"
      },
      {
        "title": "Phần 138",
        "link": "/truyen/ac-doc-nu-xung-cung-bach-lien-hoa-xuyen-/phan-138-XnWvrsQsRA1Mclgw"
      },
      {
        "title": "Phần 139",
        "link": "/truyen/ac-doc-nu-xung-cung-bach-lien-hoa-xuyen-/phan-139-XnWvrsQsRA1Mclgx"
      },
      {
        "title": "Phần 140",
        "link": "/truyen/ac-doc-nu-xung-cung-bach-lien-hoa-xuyen-/phan-140-XnWvrsQsRA1Mclgy"
      },
      {
        "title": "Phần 141",
        "link": "/truyen/ac-doc-nu-xung-cung-bach-lien-hoa-xuyen-/phan-141-XnWvrsQsRA1Mclgz"
      },
      {
        "title": "Phần 142",
        "link": "/truyen/ac-doc-nu-xung-cung-bach-lien-hoa-xuyen-/phan-142-XnWvrsQsRA1Mclg0"
      },
      {
        "title": "Phần 143",
        "link": "/truyen/ac-doc-nu-xung-cung-bach-lien-hoa-xuyen-/phan-143-XnWvrsQsRA1Mclg1"
      },
      {
        "title": "Phần 144",
        "link": "/truyen/ac-doc-nu-xung-cung-bach-lien-hoa-xuyen-/phan-144-XnWvrsQsRA1Mclg2"
      },
      {
        "title": "Phần 145",
        "link": "/truyen/ac-doc-nu-xung-cung-bach-lien-hoa-xuyen-/phan-145-XnWvrsQsRA1Mclg3"
      },
      {
        "title": "Phần 146",
        "link": "/truyen/ac-doc-nu-xung-cung-bach-lien-hoa-xuyen-/phan-146-XnWvrsQsRA1Mclg4"
      },
      {
        "title": "Phần 147",
        "link": "/truyen/ac-doc-nu-xung-cung-bach-lien-hoa-xuyen-/phan-147-XnWvrsQsRA1Mclg5"
      },
      {
        "title": "Phần 148",
        "link": "/truyen/ac-doc-nu-xung-cung-bach-lien-hoa-xuyen-/phan-148-XnWvrsQsRA1Mclg6"
      },
      {
        "title": "Phần 149",
        "link": "/truyen/ac-doc-nu-xung-cung-bach-lien-hoa-xuyen-/phan-149-XnWvrsQsRA1Mclg7"
      },
      {
        "title": "Phần 150",
        "link": "/truyen/ac-doc-nu-xung-cung-bach-lien-hoa-xuyen-/phan-150-XnWvrsQsRA1Mclg8"
      },
      {
        "title": "Phần 151",
        "link": "/truyen/ac-doc-nu-xung-cung-bach-lien-hoa-xuyen-/phan-151-XnWvrsQsRA1Mclg9"
      },
      {
        "title": "Phần 152",
        "link": "/truyen/ac-doc-nu-xung-cung-bach-lien-hoa-xuyen-/phan-152-XnWvrsQsRA1Mclg%7E"
      },
      {
        "title": "Phần 153",
        "link": "/truyen/ac-doc-nu-xung-cung-bach-lien-hoa-xuyen-/phan-153-XnWvrsQsRA1Mclg_"
      },
      {
        "title": "Phần 154",
        "link": "/truyen/ac-doc-nu-xung-cung-bach-lien-hoa-xuyen-/phan-154-XnWvrsQsRA1MclhA"
      },
      {
        "title": "Phần 155",
        "link": "/truyen/ac-doc-nu-xung-cung-bach-lien-hoa-xuyen-/phan-155-XnWvrsQsRA1MclhB"
      },
      {
        "title": "Phần 156",
        "link": "/truyen/ac-doc-nu-xung-cung-bach-lien-hoa-xuyen-/phan-156-XnWvrsQsRA1MclhC"
      },
      {
        "title": "Phần 157",
        "link": "/truyen/ac-doc-nu-xung-cung-bach-lien-hoa-xuyen-/phan-157-XnWvrsQsRA1MclhD"
      },
      {
        "title": "Phần 158",
        "link": "/truyen/ac-doc-nu-xung-cung-bach-lien-hoa-xuyen-/phan-158-XnWvrsQsRA1MclhE"
      },
      {
        "title": "Phần 159",
        "link": "/truyen/ac-doc-nu-xung-cung-bach-lien-hoa-xuyen-/phan-159-XnWvrsQsRA1MclhF"
      },
      {
        "title": "Phần 160",
        "link": "/truyen/ac-doc-nu-xung-cung-bach-lien-hoa-xuyen-/phan-160-XnWvrsQsRA1MclhG"
      },
      {
        "title": "Phần 161",
        "link": "/truyen/ac-doc-nu-xung-cung-bach-lien-hoa-xuyen-/phan-161-XnWvrsQsRA1MclhH"
      },
      {
        "title": "Phần 162",
        "link": "/truyen/ac-doc-nu-xung-cung-bach-lien-hoa-xuyen-/phan-162-XnWvrsQsRA1MclhI"
      },
      {
        "title": "Phần 163",
        "link": "/truyen/ac-doc-nu-xung-cung-bach-lien-hoa-xuyen-/phan-163-XnWvrsQsRA1MclhJ"
      },
      {
        "title": "Phần 164",
        "link": "/truyen/ac-doc-nu-xung-cung-bach-lien-hoa-xuyen-/phan-164-XnWvrsQsRA1MclhK"
      },
      {
        "title": "Phần 165",
        "link": "/truyen/ac-doc-nu-xung-cung-bach-lien-hoa-xuyen-/phan-165-XnWvrsQsRA1MclhL"
      },
      {
        "title": "Phần 166",
        "link": "/truyen/ac-doc-nu-xung-cung-bach-lien-hoa-xuyen-/phan-166-XnWvrsQsRA1MclhM"
      },
      {
        "title": "Phần 167",
        "link": "/truyen/ac-doc-nu-xung-cung-bach-lien-hoa-xuyen-/phan-167-XnWvrsQsRA1MclhN"
      },
      {
        "title": "Phần 168",
        "link": "/truyen/ac-doc-nu-xung-cung-bach-lien-hoa-xuyen-/phan-168-XnWvrsQsRA1MclhO"
      },
      {
        "title": "Phần 169",
        "link": "/truyen/ac-doc-nu-xung-cung-bach-lien-hoa-xuyen-/phan-169-XnWvrsQsRA1MclhP"
      },
      {
        "title": "Phần 170",
        "link": "/truyen/ac-doc-nu-xung-cung-bach-lien-hoa-xuyen-/phan-170-XnWvrsQsRA1MclhQ"
      },
      {
        "title": "Phần 171",
        "link": "/truyen/ac-doc-nu-xung-cung-bach-lien-hoa-xuyen-/phan-171-XnWvrsQsRA1MclhR"
      },
      {
        "title": "Phần 172",
        "link": "/truyen/ac-doc-nu-xung-cung-bach-lien-hoa-xuyen-/phan-172-XnWvrsQsRA1MclhS"
      },
      {
        "title": "Phần 173",
        "link": "/truyen/ac-doc-nu-xung-cung-bach-lien-hoa-xuyen-/phan-173-XnWvrsQsRA1MclhT"
      },
      {
        "title": "Phần 174",
        "link": "/truyen/ac-doc-nu-xung-cung-bach-lien-hoa-xuyen-/phan-174-XnWvrsQsRA1MclhU"
      },
      {
        "title": "Phần 175",
        "link": "/truyen/ac-doc-nu-xung-cung-bach-lien-hoa-xuyen-/phan-175-XnWvrsQsRA1MclhV"
      },
      {
        "title": "Phần 176",
        "link": "/truyen/ac-doc-nu-xung-cung-bach-lien-hoa-xuyen-/phan-176-XnWvrsQsRA1MclhW"
      },
      {
        "title": "Phần 177",
        "link": "/truyen/ac-doc-nu-xung-cung-bach-lien-hoa-xuyen-/phan-177-XnWvrsQsRA1MclhX"
      },
      {
        "title": "Phần 178",
        "link": "/truyen/ac-doc-nu-xung-cung-bach-lien-hoa-xuyen-/phan-178-XnWvrsQsRA1MclhY"
      },
      {
        "title": "Phần 179",
        "link": "/truyen/ac-doc-nu-xung-cung-bach-lien-hoa-xuyen-/phan-179-XnWvrsQsRA1MclhZ"
      },
      {
        "title": "Phần 180",
        "link": "/truyen/ac-doc-nu-xung-cung-bach-lien-hoa-xuyen-/phan-180-XnWvrsQsRA1Mclha"
      },
      {
        "title": "Phần 181",
        "link": "/truyen/ac-doc-nu-xung-cung-bach-lien-hoa-xuyen-/phan-181-XnWvrsQsRA1Mclhb"
      },
      {
        "title": "Phần 182",
        "link": "/truyen/ac-doc-nu-xung-cung-bach-lien-hoa-xuyen-/phan-182-XnWvrsQsRA1Mclhc"
      },
      {
        "title": "Phần 183",
        "link": "/truyen/ac-doc-nu-xung-cung-bach-lien-hoa-xuyen-/phan-183-XnWvrsQsRA1Mclhd"
      },
      {
        "title": "Phần 184",
        "link": "/truyen/ac-doc-nu-xung-cung-bach-lien-hoa-xuyen-/phan-184-XnWvrsQsRA1Mclhe"
      },
      {
        "title": "Phần 185",
        "link": "/truyen/ac-doc-nu-xung-cung-bach-lien-hoa-xuyen-/phan-185-XnWvrsQsRA1Mclhf"
      },
      {
        "title": "Phần 186",
        "link": "/truyen/ac-doc-nu-xung-cung-bach-lien-hoa-xuyen-/phan-186-XnWvrsQsRA1Mclhg"
      },
      {
        "title": "Phần 187",
        "link": "/truyen/ac-doc-nu-xung-cung-bach-lien-hoa-xuyen-/phan-187-XnWvrsQsRA1Mclhh"
      },
      {
        "title": "Phần 188",
        "link": "/truyen/ac-doc-nu-xung-cung-bach-lien-hoa-xuyen-/phan-188-XnWvrsQsRA1Mclhi"
      },
      {
        "title": "Phần 189",
        "link": "/truyen/ac-doc-nu-xung-cung-bach-lien-hoa-xuyen-/phan-189-XnWvrsQsRA1Mclhj"
      },
      {
        "title": "Phần 190",
        "link": "/truyen/ac-doc-nu-xung-cung-bach-lien-hoa-xuyen-/phan-190-XnWvrsQsRA1Mclhk"
      },
      {
        "title": "Phần 191",
        "link": "/truyen/ac-doc-nu-xung-cung-bach-lien-hoa-xuyen-/phan-191-XnWvrsQsRA1Mclhl"
      },
      {
        "title": "Phần 192",
        "link": "/truyen/ac-doc-nu-xung-cung-bach-lien-hoa-xuyen-/phan-192-XnWvrsQsRA1Mclhm"
      },
      {
        "title": "Phần 193",
        "link": "/truyen/ac-doc-nu-xung-cung-bach-lien-hoa-xuyen-/phan-193-XnWvrsQsRA1Mclhn"
      },
      {
        "title": "Phần 194",
        "link": "/truyen/ac-doc-nu-xung-cung-bach-lien-hoa-xuyen-/phan-194-XnWvrsQsRA1Mclho"
      },
      {
        "title": "Phần 195",
        "link": "/truyen/ac-doc-nu-xung-cung-bach-lien-hoa-xuyen-/phan-195-XnWvrsQsRA1Mclhp"
      },
      {
        "title": "Phần 196",
        "link": "/truyen/ac-doc-nu-xung-cung-bach-lien-hoa-xuyen-/phan-196-XnWvrsQsRA1Mclhq"
      },
      {
        "title": "Phần 197",
        "link": "/truyen/ac-doc-nu-xung-cung-bach-lien-hoa-xuyen-/phan-197-XnWvrsQsRA1Mclhr"
      },
      {
        "title": "Phần 198",
        "link": "/truyen/ac-doc-nu-xung-cung-bach-lien-hoa-xuyen-/phan-198-XnWvrsQsRA1Mclhs"
      },
      {
        "title": "Phần 199",
        "link": "/truyen/ac-doc-nu-xung-cung-bach-lien-hoa-xuyen-/phan-199-XnWvrsQsRA1Mclht"
      },
      {
        "title": "Phần 200",
        "link": "/truyen/ac-doc-nu-xung-cung-bach-lien-hoa-xuyen-/phan-200-XnWvrsQsRA1Mclhu"
      },
      {
        "title": "Phần 201",
        "link": "/truyen/ac-doc-nu-xung-cung-bach-lien-hoa-xuyen-/phan-201-XnWvrsQsRA1Mclhv"
      },
      {
        "title": "Phần 202",
        "link": "/truyen/ac-doc-nu-xung-cung-bach-lien-hoa-xuyen-/phan-202-XnWvrsQsRA1Mclhw"
      },
      {
        "title": "Phần 203",
        "link": "/truyen/ac-doc-nu-xung-cung-bach-lien-hoa-xuyen-/phan-203-XnWvrsQsRA1Mclhx"
      },
      {
        "title": "Phần 204",
        "link": "/truyen/ac-doc-nu-xung-cung-bach-lien-hoa-xuyen-/phan-204-XnWvrsQsRA1Mclhy"
      },
      {
        "title": "Phần 205",
        "link": "/truyen/ac-doc-nu-xung-cung-bach-lien-hoa-xuyen-/phan-205-XnWvrsQsRA1Mclhz"
      },
      {
        "title": "Phần 206",
        "link": "/truyen/ac-doc-nu-xung-cung-bach-lien-hoa-xuyen-/phan-206-XnWvrsQsRA1Mclh0"
      },
      {
        "title": "Phần 207",
        "link": "/truyen/ac-doc-nu-xung-cung-bach-lien-hoa-xuyen-/phan-207-XnWvrsQsRA1Mclh1"
      },
      {
        "title": "Phần 208",
        "link": "/truyen/ac-doc-nu-xung-cung-bach-lien-hoa-xuyen-/phan-208-XnWvrsQsRA1Mclh2"
      },
      {
        "title": "Phần 209",
        "link": "/truyen/ac-doc-nu-xung-cung-bach-lien-hoa-xuyen-/phan-209-XnWvrsQsRA1Mclh3"
      },
      {
        "title": "Phần 210",
        "link": "/truyen/ac-doc-nu-xung-cung-bach-lien-hoa-xuyen-/phan-210-XnWvrsQsRA1Mclh4"
      },
      {
        "title": "Phần 211",
        "link": "/truyen/ac-doc-nu-xung-cung-bach-lien-hoa-xuyen-/phan-211-XnWvrsQsRA1Mclh5"
      },
      {
        "title": "Phần 212",
        "link": "/truyen/ac-doc-nu-xung-cung-bach-lien-hoa-xuyen-/phan-212-XnWvrsQsRA1Mclh6"
      },
      {
        "title": "Phần 213",
        "link": "/truyen/ac-doc-nu-xung-cung-bach-lien-hoa-xuyen-/phan-213-XnWvrsQsRA1Mclh7"
      },
      {
        "title": "Phần 214",
        "link": "/truyen/ac-doc-nu-xung-cung-bach-lien-hoa-xuyen-/phan-214-XnWvrsQsRA1Mclh8"
      },
      {
        "title": "Phần 215",
        "link": "/truyen/ac-doc-nu-xung-cung-bach-lien-hoa-xuyen-/phan-215-XnWvrsQsRA1Mclh9"
      },
      {
        "title": "Phần 216",
        "link": "/truyen/ac-doc-nu-xung-cung-bach-lien-hoa-xuyen-/phan-216-XnWvrsQsRA1Mclh%7E"
      },
      {
        "title": "Phần 217",
        "link": "/truyen/ac-doc-nu-xung-cung-bach-lien-hoa-xuyen-/phan-217-XnWvrsQsRA1Mclh_"
      },
      {
        "title": "Phần 218",
        "link": "/truyen/ac-doc-nu-xung-cung-bach-lien-hoa-xuyen-/phan-218-XnWvrsQsRA1McliA"
      },
      {
        "title": "Phần 219",
        "link": "/truyen/ac-doc-nu-xung-cung-bach-lien-hoa-xuyen-/phan-219-XnWvrsQsRA1McliB"
      },
      {
        "title": "Phần 220",
        "link": "/truyen/ac-doc-nu-xung-cung-bach-lien-hoa-xuyen-/phan-220-XnWvrsQsRA1McliC"
      },
      {
        "title": "Phần 221",
        "link": "/truyen/ac-doc-nu-xung-cung-bach-lien-hoa-xuyen-/phan-221-XnWvrsQsRA1McliD"
      },
      {
        "title": "Phần 222",
        "link": "/truyen/ac-doc-nu-xung-cung-bach-lien-hoa-xuyen-/phan-222-XnWvrsQsRA1McliE"
      },
      {
        "title": "Phần 223",
        "link": "/truyen/ac-doc-nu-xung-cung-bach-lien-hoa-xuyen-/phan-223-XnWvrsQsRA1McliF"
      },
      {
        "title": "Phần 224",
        "link": "/truyen/ac-doc-nu-xung-cung-bach-lien-hoa-xuyen-/phan-224-XnWvrsQsRA1McliG"
      },
      {
        "title": "Phần 225",
        "link": "/truyen/ac-doc-nu-xung-cung-bach-lien-hoa-xuyen-/phan-225-XnWvrsQsRA1McliH"
      },
      {
        "title": "Phần 226",
        "link": "/truyen/ac-doc-nu-xung-cung-bach-lien-hoa-xuyen-/phan-226-XnWvrsQsRA1McliI"
      }
    ]
  }
]