[
  {
    "title": "Phong thuỷ tra án sư",
    "views": "39k",
    "stars": "580",
    "comments": "12",
    "hanViet": "Phong thủy tham án sư",
    "author": "Công Thụ Kiêm Bị Tiểu Hùng Bảo",
    "status": "Hoàn thành",
    "latestChapter": "Phần 126",
    "lastUpdate": "10-12-2024",
    "thanks": "278 lần",
    "genres": [
      "Nguyên sang",
      "Bách hợp",
      "Hiện đại",
      "HE",
      "Tình cảm",
      "Phong thủy",
      "Cường cường",
      "Hỗ công",
      "Kim bài đề cử 🥇",
      "Linh dị thần quái"
    ],
    "description": "Văn án:\n\nThân là lăng gia tám đời đơn truyền duy nhất người thừa kế, lăng phong nhất xem bất quá mắt, chính là có người không tin nàng một thân tổ truyền xem phong thuỷ tính thiên mệnh bản lĩnh.\n\nCái gì? Cảnh sát? Liền tính ngươi đem này giấy câu lưu chứng nằm xoài trên ta trước mặt, ném ở ta trên mặt, ta cũng sẽ không theo ngươi đi! Không riêng không đi ta buổi tối còn muốn đi nhà ngươi dưới lầu chiêu quỷ hù dọa ngươi!\n\nCái gì? Mỹ nữ cảnh sát?!\n\nÂn, thật hương.\n\nDùng ăn chỉ nam:\n\n1. Bổn chuyện xưa chỉ do hư cấu, có quan hệ phong thuỷ cùng phá án nội dung đều là ta biên.\n\n2. Này văn vì 《 đại tiểu thư tổng ở l·y h·ôn 》 diễn sinh văn, nhưng độc lập quan khán.\n\n3. Kết thúc văn 《 đại tiểu thư tổng ở l·y h·ôn 》\n\n4. Tác giả Weibo: Công thụ gồm nhiều mặt tiểu hùng bảo\n\n5. Nghe nói cất chứa tác giả chuyên mục tiểu thiên sứ đều có thể tìm được bạn gái!\n\nTag: Cường cườngLinh dị thần quáiNhân duyên tình cờ gặp gỡ\n\nTừ khóa tìm kiếm: Vai chính: Lăng phong, lãng tình ┃ vai phụ: Quá nhiều ┃ cái khác: Phong thuỷ, cảnh sát, huyền nghi",
    "chapters": [
      {
        "title": "Phần 1",
        "link": "/truyen/phong-thuy-tra-an-su/phan-1-XlobT8QsRCGRtm6H"
      },
      {
        "title": "Phần 2",
        "link": "/truyen/phong-thuy-tra-an-su/phan-2-XlobT8QsRCGRtm6I"
      },
      {
        "title": "Phần 3",
        "link": "/truyen/phong-thuy-tra-an-su/phan-3-XlobT8QsRCGRtm6J"
      },
      {
        "title": "Phần 4",
        "link": "/truyen/phong-thuy-tra-an-su/phan-4-XlobT8QsRCGRtm6K"
      },
      {
        "title": "Phần 5",
        "link": "/truyen/phong-thuy-tra-an-su/phan-5-XlobT8QsRCGRtm6L"
      },
      {
        "title": "Phần 6",
        "link": "/truyen/phong-thuy-tra-an-su/phan-6-XlobT8QsRCGRtm6M"
      },
      {
        "title": "Phần 7",
        "link": "/truyen/phong-thuy-tra-an-su/phan-7-XlobT8QsRCGRtm6N"
      },
      {
        "title": "Phần 8",
        "link": "/truyen/phong-thuy-tra-an-su/phan-8-XlobT8QsRCGRtm6O"
      },
      {
        "title": "Phần 9",
        "link": "/truyen/phong-thuy-tra-an-su/phan-9-XlobT8QsRCGRtm6P"
      },
      {
        "title": "Phần 10",
        "link": "/truyen/phong-thuy-tra-an-su/phan-10-XlobT8QsRCGRtm6Q"
      },
      {
        "title": "Phần 11",
        "link": "/truyen/phong-thuy-tra-an-su/phan-11-XlobT8QsRCGRtm6R"
      },
      {
        "title": "Phần 12",
        "link": "/truyen/phong-thuy-tra-an-su/phan-12-XlobT8QsRCGRtm6S"
      },
      {
        "title": "Phần 13",
        "link": "/truyen/phong-thuy-tra-an-su/phan-13-XlobT8QsRCGRtm6T"
      },
      {
        "title": "Phần 14",
        "link": "/truyen/phong-thuy-tra-an-su/phan-14-XlobT8QsRCGRtm6U"
      },
      {
        "title": "Phần 15",
        "link": "/truyen/phong-thuy-tra-an-su/phan-15-XlobT8QsRCGRtm6V"
      },
      {
        "title": "Phần 16",
        "link": "/truyen/phong-thuy-tra-an-su/phan-16-XlobT8QsRCGRtm6W"
      },
      {
        "title": "Phần 17",
        "link": "/truyen/phong-thuy-tra-an-su/phan-17-XlobT8QsRCGRtm6X"
      },
      {
        "title": "Phần 18",
        "link": "/truyen/phong-thuy-tra-an-su/phan-18-XlobT8QsRCGRtm6Y"
      },
      {
        "title": "Phần 19",
        "link": "/truyen/phong-thuy-tra-an-su/phan-19-XlobT8QsRCGRtm6Z"
      },
      {
        "title": "Phần 20",
        "link": "/truyen/phong-thuy-tra-an-su/phan-20-XlobT8QsRCGRtm6a"
      },
      {
        "title": "Phần 21",
        "link": "/truyen/phong-thuy-tra-an-su/phan-21-XlobT8QsRCGRtm6b"
      },
      {
        "title": "Phần 22",
        "link": "/truyen/phong-thuy-tra-an-su/phan-22-XlobT8QsRCGRtm6c"
      },
      {
        "title": "Phần 23",
        "link": "/truyen/phong-thuy-tra-an-su/phan-23-XlobT8QsRCGRtm6d"
      },
      {
        "title": "Phần 24",
        "link": "/truyen/phong-thuy-tra-an-su/phan-24-XlobT8QsRCGRtm6e"
      },
      {
        "title": "Phần 25",
        "link": "/truyen/phong-thuy-tra-an-su/phan-25-XlobT8QsRCGRtm6f"
      },
      {
        "title": "Phần 26",
        "link": "/truyen/phong-thuy-tra-an-su/phan-26-XlobT8QsRCGRtm6g"
      },
      {
        "title": "Phần 27",
        "link": "/truyen/phong-thuy-tra-an-su/phan-27-XlobT8QsRCGRtm6h"
      },
      {
        "title": "Phần 28",
        "link": "/truyen/phong-thuy-tra-an-su/phan-28-XlobT8QsRCGRtm6i"
      },
      {
        "title": "Phần 29",
        "link": "/truyen/phong-thuy-tra-an-su/phan-29-XlobT8QsRCGRtm6j"
      },
      {
        "title": "Phần 30",
        "link": "/truyen/phong-thuy-tra-an-su/phan-30-XlobT8QsRCGRtm6k"
      },
      {
        "title": "Phần 31",
        "link": "/truyen/phong-thuy-tra-an-su/phan-31-XlobT8QsRCGRtm6l"
      },
      {
        "title": "Phần 32",
        "link": "/truyen/phong-thuy-tra-an-su/phan-32-XlobT8QsRCGRtm6m"
      },
      {
        "title": "Phần 33",
        "link": "/truyen/phong-thuy-tra-an-su/phan-33-XlobT8QsRCGRtm6n"
      },
      {
        "title": "Phần 34",
        "link": "/truyen/phong-thuy-tra-an-su/phan-34-XlobT8QsRCGRtm6o"
      },
      {
        "title": "Phần 35",
        "link": "/truyen/phong-thuy-tra-an-su/phan-35-XlobT8QsRCGRtm6p"
      },
      {
        "title": "Phần 36",
        "link": "/truyen/phong-thuy-tra-an-su/phan-36-XlobT8QsRCGRtm6q"
      },
      {
        "title": "Phần 37",
        "link": "/truyen/phong-thuy-tra-an-su/phan-37-XlobT8QsRCGRtm6r"
      },
      {
        "title": "Phần 38",
        "link": "/truyen/phong-thuy-tra-an-su/phan-38-XlobT8QsRCGRtm6s"
      },
      {
        "title": "Phần 39",
        "link": "/truyen/phong-thuy-tra-an-su/phan-39-XlobT8QsRCGRtm6t"
      },
      {
        "title": "Phần 40",
        "link": "/truyen/phong-thuy-tra-an-su/phan-40-XlobT8QsRCGRtm6u"
      },
      {
        "title": "Phần 41",
        "link": "/truyen/phong-thuy-tra-an-su/phan-41-XlobT8QsRCGRtm6v"
      },
      {
        "title": "Phần 42",
        "link": "/truyen/phong-thuy-tra-an-su/phan-42-XlobT8QsRCGRtm6w"
      },
      {
        "title": "Phần 43",
        "link": "/truyen/phong-thuy-tra-an-su/phan-43-XlobT8QsRCGRtm6x"
      },
      {
        "title": "Phần 44",
        "link": "/truyen/phong-thuy-tra-an-su/phan-44-XlobT8QsRCGRtm6y"
      },
      {
        "title": "Phần 45",
        "link": "/truyen/phong-thuy-tra-an-su/phan-45-XlobT8QsRCGRtm6z"
      },
      {
        "title": "Phần 46",
        "link": "/truyen/phong-thuy-tra-an-su/phan-46-XlobT8QsRCGRtm60"
      },
      {
        "title": "Phần 47",
        "link": "/truyen/phong-thuy-tra-an-su/phan-47-XlobT8QsRCGRtm61"
      },
      {
        "title": "Phần 48",
        "link": "/truyen/phong-thuy-tra-an-su/phan-48-XlobT8QsRCGRtm62"
      },
      {
        "title": "Phần 49",
        "link": "/truyen/phong-thuy-tra-an-su/phan-49-XlobT8QsRCGRtm63"
      },
      {
        "title": "Phần 50",
        "link": "/truyen/phong-thuy-tra-an-su/phan-50-XlobT8QsRCGRtm64"
      },
      {
        "title": "Phần 51",
        "link": "/truyen/phong-thuy-tra-an-su/phan-51-XlobT8QsRCGRtm65"
      },
      {
        "title": "Phần 52",
        "link": "/truyen/phong-thuy-tra-an-su/phan-52-XlobT8QsRCGRtm66"
      },
      {
        "title": "Phần 53",
        "link": "/truyen/phong-thuy-tra-an-su/phan-53-XlobT8QsRCGRtm67"
      },
      {
        "title": "Phần 54",
        "link": "/truyen/phong-thuy-tra-an-su/phan-54-XlobT8QsRCGRtm68"
      },
      {
        "title": "Phần 55",
        "link": "/truyen/phong-thuy-tra-an-su/phan-55-XlobT8QsRCGRtm69"
      },
      {
        "title": "Phần 56",
        "link": "/truyen/phong-thuy-tra-an-su/phan-56-XlobT8QsRCGRtm6%7E"
      },
      {
        "title": "Phần 57",
        "link": "/truyen/phong-thuy-tra-an-su/phan-57-XlobT8QsRCGRtm6_"
      },
      {
        "title": "Phần 58",
        "link": "/truyen/phong-thuy-tra-an-su/phan-58-XlobT8QsRCGRtm7A"
      },
      {
        "title": "Phần 59",
        "link": "/truyen/phong-thuy-tra-an-su/phan-59-XlobT8QsRCGRtm7B"
      },
      {
        "title": "Phần 60",
        "link": "/truyen/phong-thuy-tra-an-su/phan-60-XlobT8QsRCGRtm7C"
      },
      {
        "title": "Phần 61",
        "link": "/truyen/phong-thuy-tra-an-su/phan-61-XlobT8QsRCGRtm7D"
      },
      {
        "title": "Phần 62",
        "link": "/truyen/phong-thuy-tra-an-su/phan-62-XlobT8QsRCGRtm7E"
      },
      {
        "title": "Phần 63",
        "link": "/truyen/phong-thuy-tra-an-su/phan-63-XlobT8QsRCGRtm7F"
      },
      {
        "title": "Phần 64",
        "link": "/truyen/phong-thuy-tra-an-su/phan-64-XlobT8QsRCGRtm7G"
      },
      {
        "title": "Phần 65",
        "link": "/truyen/phong-thuy-tra-an-su/phan-65-XlobT8QsRCGRtm7H"
      },
      {
        "title": "Phần 66",
        "link": "/truyen/phong-thuy-tra-an-su/phan-66-XlobT8QsRCGRtm7I"
      },
      {
        "title": "Phần 67",
        "link": "/truyen/phong-thuy-tra-an-su/phan-67-XlobT8QsRCGRtm7J"
      },
      {
        "title": "Phần 68",
        "link": "/truyen/phong-thuy-tra-an-su/phan-68-XlobT8QsRCGRtm7K"
      },
      {
        "title": "Phần 69",
        "link": "/truyen/phong-thuy-tra-an-su/phan-69-XlobT8QsRCGRtm7L"
      },
      {
        "title": "Phần 70",
        "link": "/truyen/phong-thuy-tra-an-su/phan-70-XlobT8QsRCGRtm7M"
      },
      {
        "title": "Phần 71",
        "link": "/truyen/phong-thuy-tra-an-su/phan-71-XlobT8QsRCGRtm7N"
      },
      {
        "title": "Phần 72",
        "link": "/truyen/phong-thuy-tra-an-su/phan-72-XlobT8QsRCGRtm7O"
      },
      {
        "title": "Phần 73",
        "link": "/truyen/phong-thuy-tra-an-su/phan-73-XlobT8QsRCGRtm7P"
      },
      {
        "title": "Phần 74",
        "link": "/truyen/phong-thuy-tra-an-su/phan-74-XlobT8QsRCGRtm7Q"
      },
      {
        "title": "Phần 75",
        "link": "/truyen/phong-thuy-tra-an-su/phan-75-XlobT8QsRCGRtm7R"
      },
      {
        "title": "Phần 76",
        "link": "/truyen/phong-thuy-tra-an-su/phan-76-XlobT8QsRCGRtm7S"
      },
      {
        "title": "Phần 77",
        "link": "/truyen/phong-thuy-tra-an-su/phan-77-XlobT8QsRCGRtm7T"
      },
      {
        "title": "Phần 78",
        "link": "/truyen/phong-thuy-tra-an-su/phan-78-XlobT8QsRCGRtm7U"
      },
      {
        "title": "Phần 79",
        "link": "/truyen/phong-thuy-tra-an-su/phan-79-XlobT8QsRCGRtm7V"
      },
      {
        "title": "Phần 80",
        "link": "/truyen/phong-thuy-tra-an-su/phan-80-XlobT8QsRCGRtm7W"
      },
      {
        "title": "Phần 81",
        "link": "/truyen/phong-thuy-tra-an-su/phan-81-XlobT8QsRCGRtm7X"
      },
      {
        "title": "Phần 82",
        "link": "/truyen/phong-thuy-tra-an-su/phan-82-XlobT8QsRCGRtm7Y"
      },
      {
        "title": "Phần 83",
        "link": "/truyen/phong-thuy-tra-an-su/phan-83-XlobT8QsRCGRtm7Z"
      },
      {
        "title": "Phần 84",
        "link": "/truyen/phong-thuy-tra-an-su/phan-84-XlobT8QsRCGRtm7a"
      },
      {
        "title": "Phần 85",
        "link": "/truyen/phong-thuy-tra-an-su/phan-85-XlobT8QsRCGRtm7b"
      },
      {
        "title": "Phần 86",
        "link": "/truyen/phong-thuy-tra-an-su/phan-86-XlobT8QsRCGRtm7c"
      },
      {
        "title": "Phần 87",
        "link": "/truyen/phong-thuy-tra-an-su/phan-87-XlobT8QsRCGRtm7d"
      },
      {
        "title": "Phần 88",
        "link": "/truyen/phong-thuy-tra-an-su/phan-88-XlobT8QsRCGRtm7e"
      },
      {
        "title": "Phần 89",
        "link": "/truyen/phong-thuy-tra-an-su/phan-89-XlobT8QsRCGRtm7f"
      },
      {
        "title": "Phần 90",
        "link": "/truyen/phong-thuy-tra-an-su/phan-90-XlobT8QsRCGRtm7g"
      },
      {
        "title": "Phần 91",
        "link": "/truyen/phong-thuy-tra-an-su/phan-91-XlobT8QsRCGRtm7h"
      },
      {
        "title": "Phần 92",
        "link": "/truyen/phong-thuy-tra-an-su/phan-92-XlobT8QsRCGRtm7i"
      },
      {
        "title": "Phần 93",
        "link": "/truyen/phong-thuy-tra-an-su/phan-93-XlobT8QsRCGRtm7j"
      },
      {
        "title": "Phần 94",
        "link": "/truyen/phong-thuy-tra-an-su/phan-94-XlobT8QsRCGRtm7k"
      },
      {
        "title": "Phần 95",
        "link": "/truyen/phong-thuy-tra-an-su/phan-95-XlobT8QsRCGRtm7l"
      },
      {
        "title": "Phần 96",
        "link": "/truyen/phong-thuy-tra-an-su/phan-96-XlobT8QsRCGRtm7m"
      },
      {
        "title": "Phần 97",
        "link": "/truyen/phong-thuy-tra-an-su/phan-97-XlobT8QsRCGRtm7n"
      },
      {
        "title": "Phần 98",
        "link": "/truyen/phong-thuy-tra-an-su/phan-98-XlobT8QsRCGRtm7o"
      },
      {
        "title": "Phần 99",
        "link": "/truyen/phong-thuy-tra-an-su/phan-99-XlobT8QsRCGRtm7p"
      },
      {
        "title": "Phần 100",
        "link": "/truyen/phong-thuy-tra-an-su/phan-100-XlobT8QsRCGRtm7q"
      },
      {
        "title": "Phần 101",
        "link": "/truyen/phong-thuy-tra-an-su/phan-101-XlobT8QsRCGRtm7r"
      },
      {
        "title": "Phần 102",
        "link": "/truyen/phong-thuy-tra-an-su/phan-102-XlobT8QsRCGRtm7s"
      },
      {
        "title": "Phần 103",
        "link": "/truyen/phong-thuy-tra-an-su/phan-103-XlobT8QsRCGRtm7t"
      },
      {
        "title": "Phần 104",
        "link": "/truyen/phong-thuy-tra-an-su/phan-104-XlobT8QsRCGRtm7u"
      },
      {
        "title": "Phần 105",
        "link": "/truyen/phong-thuy-tra-an-su/phan-105-XlobT8QsRCGRtm7v"
      },
      {
        "title": "Phần 106",
        "link": "/truyen/phong-thuy-tra-an-su/phan-106-XlobT8QsRCGRtm7w"
      },
      {
        "title": "Phần 107",
        "link": "/truyen/phong-thuy-tra-an-su/phan-107-XlobT8QsRCGRtm7x"
      },
      {
        "title": "Phần 108",
        "link": "/truyen/phong-thuy-tra-an-su/phan-108-XlobT8QsRCGRtm7y"
      },
      {
        "title": "Phần 109",
        "link": "/truyen/phong-thuy-tra-an-su/phan-109-XlobT8QsRCGRtm7z"
      },
      {
        "title": "Phần 110",
        "link": "/truyen/phong-thuy-tra-an-su/phan-110-XlobT8QsRCGRtm70"
      },
      {
        "title": "Phần 111",
        "link": "/truyen/phong-thuy-tra-an-su/phan-111-XlobT8QsRCGRtm71"
      },
      {
        "title": "Phần 112",
        "link": "/truyen/phong-thuy-tra-an-su/phan-112-XlobT8QsRCGRtm72"
      },
      {
        "title": "Phần 113",
        "link": "/truyen/phong-thuy-tra-an-su/phan-113-XlobT8QsRCGRtm73"
      },
      {
        "title": "Phần 114",
        "link": "/truyen/phong-thuy-tra-an-su/phan-114-XlobT8QsRCGRtm74"
      },
      {
        "title": "Phần 115",
        "link": "/truyen/phong-thuy-tra-an-su/phan-115-XlobT8QsRCGRtm75"
      },
      {
        "title": "Phần 116",
        "link": "/truyen/phong-thuy-tra-an-su/phan-116-XlobT8QsRCGRtm76"
      },
      {
        "title": "Phần 117",
        "link": "/truyen/phong-thuy-tra-an-su/phan-117-XlobT8QsRCGRtm77"
      },
      {
        "title": "Phần 118",
        "link": "/truyen/phong-thuy-tra-an-su/phan-118-XlobT8QsRCGRtm78"
      },
      {
        "title": "Phần 119",
        "link": "/truyen/phong-thuy-tra-an-su/phan-119-XlobT8QsRCGRtm79"
      },
      {
        "title": "Phần 120",
        "link": "/truyen/phong-thuy-tra-an-su/phan-120-XlobT8QsRCGRtm7%7E"
      },
      {
        "title": "Phần 121",
        "link": "/truyen/phong-thuy-tra-an-su/phan-121-XlobT8QsRCGRtm7_"
      },
      {
        "title": "Phần 122",
        "link": "/truyen/phong-thuy-tra-an-su/phan-122-XlobT8QsRCGRtm8A"
      },
      {
        "title": "Phần 123",
        "link": "/truyen/phong-thuy-tra-an-su/phan-123-XlobT8QsRCGRtm8B"
      },
      {
        "title": "Phần 124",
        "link": "/truyen/phong-thuy-tra-an-su/phan-124-XlobT8QsRCGRtm8C"
      },
      {
        "title": "Phần 125",
        "link": "/truyen/phong-thuy-tra-an-su/phan-125-XlobT8QsRCGRtm8D"
      },
      {
        "title": "Phần 126",
        "link": "/truyen/phong-thuy-tra-an-su/phan-126-XlobT8QsRCGRtm8E"
      }
    ]
  }
]